mpl_axes_aligner/__init__.py
mpl_axes_aligner/align.py
mpl_axes_aligner/shift.py
mpl_axes_aligner-1.3.dist-info/LICENSE
mpl_axes_aligner-1.3.dist-info/METADATA
mpl_axes_aligner-1.3.dist-info/WHEEL
mpl_axes_aligner-1.3.dist-info/top_level.txt
mpl_axes_aligner-1.3.dist-info/RECORD
