Metadata-Version: 2.1
Name: mpl-axes-aligner
Version: 1.3
Summary: Adjust the plotting range of matplotlib.axes.Axes objects to align the origins with the given position
Home-page: https://github.com/ryutok/mpl_axes_aligner
Author: ryutok
Author-email: ryutokm+os@gmail.com
License: MIT
Platform: UNKNOWN
Classifier: Programming Language :: Python :: 2.7
Classifier: Programming Language :: Python :: 3.7
Classifier: Programming Language :: Python :: 3.8
Classifier: Programming Language :: Python :: 3.9
Classifier: License :: OSI Approved :: MIT License
Classifier: Operating System :: OS Independent
Classifier: Topic :: Scientific/Engineering :: Visualization
Requires-Dist: matplotlib
Provides-Extra: doc
Requires-Dist: sphinx-rtd-theme ; extra == 'doc'
Provides-Extra: release
Requires-Dist: twine ; extra == 'release'
Provides-Extra: test
Requires-Dist: pytest-flake8 ; extra == 'test'
Requires-Dist: pytest-cov ; extra == 'test'
